Metadata-Version: 2.4
Name: mseep-axiom-mcp
Version: 0.1.7
Summary: 🚀 MCP framework that unlocks truly scalable AI systems with zero friction
Author-email: mseep <support@skydeck.ai>
License-File: LICENSE
Keywords: ai,axiom,llm,machine-learning,mcp,model-context-protocol
Classifier: Development Status :: 4 - Beta
Classifier: Intended Audience :: Developers
Classifier: License :: OSI Approved :: GNU General Public License v3 (GPLv3)
Classifier: Operating System :: OS Independent
Classifier: Programming Language :: Python :: 3.11
Classifier: Programming Language :: Python :: 3.12
Classifier: Topic :: Scientific/Engineering :: Artificial Intelligence
Classifier: Topic :: Software Development :: Libraries :: Python Modules
Requires-Python: <3.13,>=3.11
Requires-Dist: aiofiles>=23.2.1
Requires-Dist: aiohttp>=3.8.0
Requires-Dist: aiosqlite>=0.21.0
Requires-Dist: cachetools>=5.3.2
Requires-Dist: jsonschema>=4.23.0
Requires-Dist: mcp<2.0.0,>=1.0.0
Requires-Dist: opentelemetry-api>=1.21.0
Requires-Dist: opentelemetry-sdk>=1.21.0
Requires-Dist: pydantic-settings>=2.6.1
Requires-Dist: pydantic<3.0.0,>=2.5.3
Requires-Dist: python-dotenv>=1.0.1
Requires-Dist: typer>=0.9.0
Requires-Dist: watchdog>=6.0.0
Provides-Extra: db
Requires-Dist: aioredis>=2.0.1; extra == 'db'
Requires-Dist: asyncpg>=0.29.0; extra == 'db'
Requires-Dist: msgpack>=1.0.7; extra == 'db'
Provides-Extra: dev
Requires-Dist: black>=23.0; extra == 'dev'
Requires-Dist: build>=1.2.2.post1; extra == 'dev'
Requires-Dist: mypy>=1.0; extra == 'dev'
Requires-Dist: pre-commit>=3.0; extra == 'dev'
Requires-Dist: pytest-asyncio>=0.25.3; extra == 'dev'
Requires-Dist: pytest-cov>=4.0; extra == 'dev'
Requires-Dist: pytest>=7.0; extra == 'dev'
Requires-Dist: rich>=13.9.4; extra == 'dev'
Requires-Dist: ruff>=0.1.0; extra == 'dev'
Requires-Dist: twine>=6.1.0; extra == 'dev'
Requires-Dist: watchdog==6.0.0; extra == 'dev'
Provides-Extra: telemetry
Requires-Dist: opentelemetry-instrumentation>=0.42b0; extra == 'telemetry'
Requires-Dist: prometheus-client>=0.19.0; extra == 'telemetry'
Provides-Extra: validation
Requires-Dist: pydantic[email]>=2.5.3; extra == 'validation'
